{"cameraMode":{"drawMode":0,"name":"Shaded","section":"Shading Mode"},"sceneLighting":true,"audioPlay":false,"sceneViewState":{"showFog":true,"showMaterialUpdate":false,"showSkybox":true,"showFlares":true,"showImageEffects":true,"showParticleSystems":true},"in2DMode":false,"pivot":{"x":194.18780517578126,"y":10.662734985351563,"z":360.78607177734377},"rotation":{"x":-0.22982385754585267,"y":0.13808023929595948,"z":-0.03304082527756691,"w":-0.9628947973251343},"size":39.16575622558594,"orthographic":false}